[
  {
    "DATA": "2025-10-01T04:00:00.000Z",
    "VENDEDOR": "10942 - BRUNO DE SOUZA CAMARGO",
    "GRUPO GERENCIAL": "RETORNAVEL 200 ML",
    "META": 30,
    "QTDE": 0,
    "FAT": 0,
    "PM": 0
  },
  {
    "DATA": "2025-10-01T04:00:00.000Z",
    "VENDEDOR": "10943 - BRUNO DE SOUZA CAMARGO",
    "GRUPO GERENCIAL": "RETORNAVEL 600 ML",
    "META": 335,
    "QTDE": 298,
    "FAT": 8870.21,
    "PM": 29.7658
  },
  {
    "DATA": "2025-10-01T04:00:00.000Z",
    "VENDEDOR": "10944 - BRUNO DE SOUZA CAMARGO",
    "GRUPO GERENCIAL": "DESCARTAVEL 250 ML",
    "META": 65,
    "QTDE": 286,
    "FAT": 3827.01,
    "PM": 13.3812
  },
  {
    "DATA": "2025-10-01T04:00:00.000Z",
    "VENDEDOR": "10945 - BRUNO DE SOUZA CAMARGO",
    "GRUPO GERENCIAL": "DESCARTAVEL SABORES 600 ML",
    "META": 75,
    "QTDE": 33,
    "FAT": 1021.48,
    "PM": 30.9539
  },
  {
    "DATA": "2025-10-01T04:00:00.000Z",
    "VENDEDOR": "10946 - BRUNO DE SOUZA CAMARGO",
    "GRUPO GERENCIAL": "DESCARTAVEL COLA OURO 2000 ML",
    "META": 345,
    "QTDE": 197,
    "FAT": 5246.47,
    "PM": 26.6318
  },
  {
    "DATA": "2025-10-01T04:00:00.000Z",
    "VENDEDOR": "10947 - BRUNO DE SOUZA CAMARGO",
    "GRUPO GERENCIAL": "DESCARTAVEL SABORES 2000 ML",
    "META": 2365,
    "QTDE": 2175,
    "FAT": 53103.49,
    "PM": 24.4154
  },
  {
    "DATA": "2025-10-01T04:00:00.000Z",
    "VENDEDOR": "10948 - BRUNO DE SOUZA CAMARGO",
    "GRUPO GERENCIAL": "DESCARTAVEL BC 2000 ML",
    "META": 50,
    "QTDE": 49,
    "FAT": 987.83,
    "PM": 20.1598
  },
  {
    "DATA": "2025-10-01T04:00:00.000Z",
    "VENDEDOR": "10949 - BRUNO DE SOUZA CAMARGO",
    "GRUPO GERENCIAL": "DESCARTAVEL AGUA ",
    "META": 960,
    "QTDE": 1208,
    "FAT": 17580.86,
    "PM": 14.5537
  },
  {
    "DATA": "2025-10-01T04:00:00.000Z",
    "VENDEDOR": "10950 - BRUNO DE SOUZA CAMARGO",
    "GRUPO GERENCIAL": "DESCARTAVEL ENERGETICO",
    "META": 60,
    "QTDE": 12,
    "FAT": 421.82,
    "PM": 35.1517
  },
  {
    "DATA": "2025-10-01T04:00:00.000Z",
    "VENDEDOR": "10951 - BRUNO DE SOUZA CAMARGO",
    "GRUPO GERENCIAL": "SUCO RECONSTITUIDO GAROTO",
    "META": 387,
    "QTDE": 190,
    "FAT": 16829.26,
    "PM": 88.5751
  },
  {
    "DATA": "2025-10-01T04:00:00.000Z",
    "VENDEDOR": "10952 - BRUNO DE SOUZA CAMARGO",
    "GRUPO GERENCIAL": "SUCOS",
    "META": 35,
    "QTDE": 11,
    "FAT": 1238.28,
    "PM": 112.5709
  },
  {
    "DATA": "2025-10-01T04:00:00.000Z",
    "VENDEDOR": "420 - COMERCIO E DIST BEBIDAS GAROTO LTDA",
    "GRUPO GERENCIAL": "RETORNAVEL 600 ML",
    "META": 0,
    "QTDE": 24,
    "FAT": 708.6,
    "PM": 29.525
  },
  {
    "DATA": "2025-10-01T04:00:00.000Z",
    "VENDEDOR": "421 - COMERCIO E DIST BEBIDAS GAROTO LTDA",
    "GRUPO GERENCIAL": "DESCARTAVEL 250 ML",
    "META": 0,
    "QTDE": 39,
    "FAT": 448,
    "PM": 11.4872
  },
  {
    "DATA": "2025-10-01T04:00:00.000Z",
    "VENDEDOR": "422 - COMERCIO E DIST BEBIDAS GAROTO LTDA",
    "GRUPO GERENCIAL": "DESCARTAVEL SABORES 600 ML",
    "META": 0,
    "QTDE": 9,
    "FAT": 211.5,
    "PM": 23.5
  },
  {
    "DATA": "2025-10-01T04:00:00.000Z",
    "VENDEDOR": "423 - COMERCIO E DIST BEBIDAS GAROTO LTDA",
    "GRUPO GERENCIAL": "DESCARTAVEL COLA OURO 2000 ML",
    "META": 0,
    "QTDE": 16,
    "FAT": 373.97,
    "PM": 23.3731
  },
  {
    "DATA": "2025-10-01T04:00:00.000Z",
    "VENDEDOR": "424 - COMERCIO E DIST BEBIDAS GAROTO LTDA",
    "GRUPO GERENCIAL": "DESCARTAVEL SABORES 2000 ML",
    "META": 0,
    "QTDE": 83,
    "FAT": 1900.5,
    "PM": 22.8976
  },
  {
    "DATA": "2025-10-01T04:00:00.000Z",
    "VENDEDOR": "425 - COMERCIO E DIST BEBIDAS GAROTO LTDA",
    "GRUPO GERENCIAL": "DESCARTAVEL AGUA ",
    "META": 0,
    "QTDE": 214,
    "FAT": 2618.22,
    "PM": 12.2347
  },
  {
    "DATA": "2025-10-01T04:00:00.000Z",
    "VENDEDOR": "426 - COMERCIO E DIST BEBIDAS GAROTO LTDA",
    "GRUPO GERENCIAL": "DESCARTAVEL ENERGETICO",
    "META": 0,
    "QTDE": 4.1667,
    "FAT": 76.6,
    "PM": 18.3839
  },
  {
    "DATA": "2025-10-01T04:00:00.000Z",
    "VENDEDOR": "427 - COMERCIO E DIST BEBIDAS GAROTO LTDA",
    "GRUPO GERENCIAL": "SUCO RECONSTITUIDO GAROTO",
    "META": 0,
    "QTDE": 35.0832,
    "FAT": 2519.69,
    "PM": 71.8204
  },
  {
    "DATA": "2025-10-01T04:00:00.000Z",
    "VENDEDOR": "428 - COMERCIO E DIST BEBIDAS GAROTO LTDA",
    "GRUPO GERENCIAL": "SUCOS",
    "META": 0,
    "QTDE": 13.6666,
    "FAT": 1310.84,
    "PM": 95.9156
  },
  {
    "DATA": "2025-10-01T04:00:00.000Z",
    "VENDEDOR": "429 - COMERCIO E DIST BEBIDAS GAROTO LTDA",
    "GRUPO GERENCIAL": "LATA BALY 473 ML",
    "META": 0,
    "QTDE": 1,
    "FAT": 36.6,
    "PM": 36.6
  },
  {
    "DATA": "2025-10-01T04:00:00.000Z",
    "VENDEDOR": "10279 - EDIVALDO FERNANDES DA SILVA",
    "GRUPO GERENCIAL": "RETORNAVEL 200 ML",
    "META": 40,
    "QTDE": 30,
    "FAT": 1618.39,
    "PM": 53.9463
  },
  {
    "DATA": "2025-10-01T04:00:00.000Z",
    "VENDEDOR": "10280 - EDIVALDO FERNANDES DA SILVA",
    "GRUPO GERENCIAL": "RETORNAVEL 600 ML",
    "META": 205,
    "QTDE": 196,
    "FAT": 8319.58,
    "PM": 42.4468
  },
  {
    "DATA": "2025-10-01T04:00:00.000Z",
    "VENDEDOR": "10281 - EDIVALDO FERNANDES DA SILVA",
    "GRUPO GERENCIAL": "DESCARTAVEL 250 ML",
    "META": 160,
    "QTDE": 98,
    "FAT": 1825.52,
    "PM": 18.6278
  },
  {
    "DATA": "2025-10-01T04:00:00.000Z",
    "VENDEDOR": "10282 - EDIVALDO FERNANDES DA SILVA",
    "GRUPO GERENCIAL": "DESCARTAVEL SABORES 600 ML",
    "META": 150,
    "QTDE": 120.0833,
    "FAT": 3487.74,
    "PM": 29.0443
  },
  {
    "DATA": "2025-10-01T04:00:00.000Z",
    "VENDEDOR": "10283 - EDIVALDO FERNANDES DA SILVA",
    "GRUPO GERENCIAL": "DESCARTAVEL COLA OURO 2000 ML",
    "META": 165,
    "QTDE": 97,
    "FAT": 2792.42,
    "PM": 28.7878
  },
  {
    "DATA": "2025-10-01T04:00:00.000Z",
    "VENDEDOR": "10284 - EDIVALDO FERNANDES DA SILVA",
    "GRUPO GERENCIAL": "DESCARTAVEL SABORES 2000 ML",
    "META": 1210,
    "QTDE": 820,
    "FAT": 22758.76,
    "PM": 27.7546
  },
  {
    "DATA": "2025-10-01T04:00:00.000Z",
    "VENDEDOR": "10285 - EDIVALDO FERNANDES DA SILVA",
    "GRUPO GERENCIAL": "DESCARTAVEL BC 2000 ML",
    "META": 50,
    "QTDE": 55,
    "FAT": 1293.6,
    "PM": 23.52
  },
  {
    "DATA": "2025-10-01T04:00:00.000Z",
    "VENDEDOR": "10286 - EDIVALDO FERNANDES DA SILVA",
    "GRUPO GERENCIAL": "DESCARTAVEL AGUA ",
    "META": 1950,
    "QTDE": 1287,
    "FAT": 20712.98,
    "PM": 16.094
  },
  {
    "DATA": "2025-10-01T04:00:00.000Z",
    "VENDEDOR": "10287 - EDIVALDO FERNANDES DA SILVA",
    "GRUPO GERENCIAL": "DESCARTAVEL ENERGETICO",
    "META": 170,
    "QTDE": 103,
    "FAT": 2885.12,
    "PM": 28.0109
  },
  {
    "DATA": "2025-10-01T04:00:00.000Z",
    "VENDEDOR": "10288 - EDIVALDO FERNANDES DA SILVA",
    "GRUPO GERENCIAL": "SUCO RECONSTITUIDO GAROTO",
    "META": 1770,
    "QTDE": 687,
    "FAT": 58711.8,
    "PM": 85.4611
  },
  {
    "DATA": "2025-10-01T04:00:00.000Z",
    "VENDEDOR": "10289 - EDIVALDO FERNANDES DA SILVA",
    "GRUPO GERENCIAL": "SUCOS",
    "META": 85,
    "QTDE": 6,
    "FAT": 596.94,
    "PM": 99.49
  },
  {
    "DATA": "2025-10-01T04:00:00.000Z",
    "VENDEDOR": "10290 - EDIVALDO FERNANDES DA SILVA",
    "GRUPO GERENCIAL": "LATA BALY 473 ML",
    "META": 0,
    "QTDE": 20,
    "FAT": 406.98,
    "PM": 20.349
  },
  {
    "DATA": "2025-10-01T04:00:00.000Z",
    "VENDEDOR": " 11311 - EDVALDO PEREIRA MACHADO",
    "GRUPO GERENCIAL": "RETORNAVEL 200 ML",
    "META": 15,
    "QTDE": 0,
    "FAT": 0,
    "PM": 0
  },
  {
    "DATA": "2025-10-01T04:00:00.000Z",
    "VENDEDOR": " 11312 - EDVALDO PEREIRA MACHADO",
    "GRUPO GERENCIAL": "RETORNAVEL 600 ML",
    "META": 385,
    "QTDE": 295,
    "FAT": 10670.62,
    "PM": 36.1716
  },
  {
    "DATA": "2025-10-01T04:00:00.000Z",
    "VENDEDOR": " 11313 - EDVALDO PEREIRA MACHADO",
    "GRUPO GERENCIAL": "DESCARTAVEL 250 ML",
    "META": 1285,
    "QTDE": 1240,
    "FAT": 14880,
    "PM": 12
  },
  {
    "DATA": "2025-10-01T04:00:00.000Z",
    "VENDEDOR": " 11314 - EDVALDO PEREIRA MACHADO",
    "GRUPO GERENCIAL": "DESCARTAVEL SABORES 600 ML",
    "META": 175,
    "QTDE": 643,
    "FAT": 13775.68,
    "PM": 21.4241
  },
  {
    "DATA": "2025-10-01T04:00:00.000Z",
    "VENDEDOR": " 11315 - EDVALDO PEREIRA MACHADO",
    "GRUPO GERENCIAL": "DESCARTAVEL COLA OURO 2000 ML",
    "META": 1310,
    "QTDE": 963,
    "FAT": 24042.58,
    "PM": 24.9663
  },
  {
    "DATA": "2025-10-01T04:00:00.000Z",
    "VENDEDOR": " 11316 - EDVALDO PEREIRA MACHADO",
    "GRUPO GERENCIAL": "DESCARTAVEL SABORES 2000 ML",
    "META": 14340,
    "QTDE": 5500,
    "FAT": 128376.41,
    "PM": 23.3412
  },
  {
    "DATA": "2025-10-01T04:00:00.000Z",
    "VENDEDOR": " 11317 - EDVALDO PEREIRA MACHADO",
    "GRUPO GERENCIAL": "DESCARTAVEL BC 2000 ML",
    "META": 50,
    "QTDE": 0,
    "FAT": 0,
    "PM": 0
  },
  {
    "DATA": "2025-10-01T04:00:00.000Z",
    "VENDEDOR": " 11318 - EDVALDO PEREIRA MACHADO",
    "GRUPO GERENCIAL": "DESCARTAVEL AGUA ",
    "META": 790,
    "QTDE": 6476,
    "FAT": 78427.23,
    "PM": 12.1104
  },
  {
    "DATA": "2025-10-01T04:00:00.000Z",
    "VENDEDOR": " 11319 - EDVALDO PEREIRA MACHADO",
    "GRUPO GERENCIAL": "DESCARTAVEL ENERGETICO",
    "META": 75,
    "QTDE": 6,
    "FAT": 210.9,
    "PM": 35.15
  },
  {
    "DATA": "2025-10-01T04:00:00.000Z",
    "VENDEDOR": " 5399 - GILMAR DE MORAIS",
    "GRUPO GERENCIAL": "RETORNAVEL 200 ML",
    "META": 75,
    "QTDE": 37,
    "FAT": 1869.7,
    "PM": 50.5324
  },
  {
    "DATA": "2025-10-01T04:00:00.000Z",
    "VENDEDOR": " 5400 - GILMAR DE MORAIS",
    "GRUPO GERENCIAL": "RETORNAVEL 600 ML",
    "META": 425,
    "QTDE": 299,
    "FAT": 13108.78,
    "PM": 43.8421
  },
  {
    "DATA": "2025-10-01T04:00:00.000Z",
    "VENDEDOR": " 5401 - GILMAR DE MORAIS",
    "GRUPO GERENCIAL": "DESCARTAVEL 250 ML",
    "META": 380,
    "QTDE": 57,
    "FAT": 1214.69,
    "PM": 21.3104
  },
  {
    "DATA": "2025-10-01T04:00:00.000Z",
    "VENDEDOR": " 5402 - GILMAR DE MORAIS",
    "GRUPO GERENCIAL": "DESCARTAVEL SABORES 600 ML",
    "META": 45,
    "QTDE": 17,
    "FAT": 497.55,
    "PM": 29.2676
  },
  {
    "DATA": "2025-10-01T04:00:00.000Z",
    "VENDEDOR": " 5403 - GILMAR DE MORAIS",
    "GRUPO GERENCIAL": "DESCARTAVEL COLA OURO 2000 ML",
    "META": 1200,
    "QTDE": 689,
    "FAT": 19142.75,
    "PM": 27.7834
  },
  {
    "DATA": "2025-10-01T04:00:00.000Z",
    "VENDEDOR": " 5404 - GILMAR DE MORAIS",
    "GRUPO GERENCIAL": "DESCARTAVEL SABORES 2000 ML",
    "META": 4410,
    "QTDE": 1538,
    "FAT": 41039.38,
    "PM": 26.6836
  },
  {
    "DATA": "2025-10-01T04:00:00.000Z",
    "VENDEDOR": " 5405 - GILMAR DE MORAIS",
    "GRUPO GERENCIAL": "DESCARTAVEL BC 2000 ML",
    "META": 50,
    "QTDE": 49,
    "FAT": 1081.92,
    "PM": 22.08
  },
  {
    "DATA": "2025-10-01T04:00:00.000Z",
    "VENDEDOR": " 5406 - GILMAR DE MORAIS",
    "GRUPO GERENCIAL": "DESCARTAVEL AGUA ",
    "META": 500,
    "QTDE": 331,
    "FAT": 5923.63,
    "PM": 17.8962
  },
  {
    "DATA": "2025-10-01T04:00:00.000Z",
    "VENDEDOR": " 5407 - GILMAR DE MORAIS",
    "GRUPO GERENCIAL": "DESCARTAVEL ENERGETICO",
    "META": 75,
    "QTDE": 12,
    "FAT": 393.6,
    "PM": 32.8
  },
  {
    "DATA": "2025-10-01T04:00:00.000Z",
    "VENDEDOR": " 5408 - GILMAR DE MORAIS",
    "GRUPO GERENCIAL": "SUCO RECONSTITUIDO GAROTO",
    "META": 899,
    "QTDE": 408,
    "FAT": 36932.59,
    "PM": 90.5211
  },
  {
    "DATA": "2025-10-01T04:00:00.000Z",
    "VENDEDOR": " 5409 - GILMAR DE MORAIS",
    "GRUPO GERENCIAL": "SUCOS",
    "META": 35,
    "QTDE": 9,
    "FAT": 764.04,
    "PM": 84.8933
  },
  {
    "DATA": "2025-10-01T04:00:00.000Z",
    "VENDEDOR": " 5410 - GILMAR DE MORAIS",
    "GRUPO GERENCIAL": "LATA BALY 473 ML",
    "META": 0,
    "QTDE": 4,
    "FAT": 95.76,
    "PM": 23.94
  },
  {
    "DATA": "2025-10-01T04:00:00.000Z",
    "VENDEDOR": " 5128 - JOAO LUIZ PRADOS",
    "GRUPO GERENCIAL": "RETORNAVEL 200 ML",
    "META": 5,
    "QTDE": 1,
    "FAT": 53.95,
    "PM": 53.95
  },
  {
    "DATA": "2025-10-01T04:00:00.000Z",
    "VENDEDOR": " 5129 - JOAO LUIZ PRADOS",
    "GRUPO GERENCIAL": "RETORNAVEL 600 ML",
    "META": 445,
    "QTDE": 259,
    "FAT": 8617.37,
    "PM": 33.2717
  },
  {
    "DATA": "2025-10-01T04:00:00.000Z",
    "VENDEDOR": " 5130 - JOAO LUIZ PRADOS",
    "GRUPO GERENCIAL": "DESCARTAVEL 250 ML",
    "META": 980,
    "QTDE": 304,
    "FAT": 4308.39,
    "PM": 14.1723
  },
  {
    "DATA": "2025-10-01T04:00:00.000Z",
    "VENDEDOR": " 5131 - JOAO LUIZ PRADOS",
    "GRUPO GERENCIAL": "DESCARTAVEL SABORES 600 ML",
    "META": 110,
    "QTDE": 130,
    "FAT": 3608.42,
    "PM": 27.7571
  },
  {
    "DATA": "2025-10-01T04:00:00.000Z",
    "VENDEDOR": " 5132 - JOAO LUIZ PRADOS",
    "GRUPO GERENCIAL": "DESCARTAVEL COLA OURO 2000 ML",
    "META": 570,
    "QTDE": 566,
    "FAT": 15473.04,
    "PM": 27.3375
  },
  {
    "DATA": "2025-10-01T04:00:00.000Z",
    "VENDEDOR": " 5133 - JOAO LUIZ PRADOS",
    "GRUPO GERENCIAL": "DESCARTAVEL SABORES 2000 ML",
    "META": 7010,
    "QTDE": 2738,
    "FAT": 64169.27,
    "PM": 23.4365
  },
  {
    "DATA": "2025-10-01T04:00:00.000Z",
    "VENDEDOR": " 5134 - JOAO LUIZ PRADOS",
    "GRUPO GERENCIAL": "DESCARTAVEL BC 2000 ML",
    "META": 50,
    "QTDE": 7,
    "FAT": 164.64,
    "PM": 23.52
  },
  {
    "DATA": "2025-10-01T04:00:00.000Z",
    "VENDEDOR": " 5135 - JOAO LUIZ PRADOS",
    "GRUPO GERENCIAL": "DESCARTAVEL AGUA ",
    "META": 575,
    "QTDE": 1171,
    "FAT": 21529.91,
    "PM": 18.3859
  },
  {
    "DATA": "2025-10-01T04:00:00.000Z",
    "VENDEDOR": " 5136 - JOAO LUIZ PRADOS",
    "GRUPO GERENCIAL": "DESCARTAVEL ENERGETICO",
    "META": 75,
    "QTDE": 34,
    "FAT": 1188.6,
    "PM": 34.9588
  },
  {
    "DATA": "2025-10-01T04:00:00.000Z",
    "VENDEDOR": " 5137 - JOAO LUIZ PRADOS",
    "GRUPO GERENCIAL": "SUCO RECONSTITUIDO GAROTO",
    "META": 354.6,
    "QTDE": 187,
    "FAT": 16288,
    "PM": 87.1016
  },
  {
    "DATA": "2025-10-01T04:00:00.000Z",
    "VENDEDOR": " 5138 - JOAO LUIZ PRADOS",
    "GRUPO GERENCIAL": "SUCOS",
    "META": 55,
    "QTDE": 0,
    "FAT": 0,
    "PM": 0
  },
  {
    "DATA": "2025-10-01T04:00:00.000Z",
    "VENDEDOR": " 5139 - JOAO LUIZ PRADOS",
    "GRUPO GERENCIAL": "LATA BALY 473 ML",
    "META": 0,
    "QTDE": 2,
    "FAT": 47.88,
    "PM": 23.94
  },
  {
    "DATA": "2025-10-01T04:00:00.000Z",
    "VENDEDOR": "7875 - VALBERICO FERREIRA DE ARAUJO",
    "GRUPO GERENCIAL": "RETORNAVEL 200 ML",
    "META": 5,
    "QTDE": 3,
    "FAT": 161.84,
    "PM": 53.9467
  },
  {
    "DATA": "2025-10-01T04:00:00.000Z",
    "VENDEDOR": "7876 - VALBERICO FERREIRA DE ARAUJO",
    "GRUPO GERENCIAL": "RETORNAVEL 600 ML",
    "META": 225,
    "QTDE": 194,
    "FAT": 9881.04,
    "PM": 50.9332
  },
  {
    "DATA": "2025-10-01T04:00:00.000Z",
    "VENDEDOR": "7877 - VALBERICO FERREIRA DE ARAUJO",
    "GRUPO GERENCIAL": "DESCARTAVEL 250 ML",
    "META": 80,
    "QTDE": 57,
    "FAT": 804.29,
    "PM": 14.1104
  },
  {
    "DATA": "2025-10-01T04:00:00.000Z",
    "VENDEDOR": "7878 - VALBERICO FERREIRA DE ARAUJO",
    "GRUPO GERENCIAL": "DESCARTAVEL SABORES 600 ML",
    "META": 45,
    "QTDE": 134,
    "FAT": 2903.04,
    "PM": 21.6645
  },
  {
    "DATA": "2025-10-01T04:00:00.000Z",
    "VENDEDOR": "7879 - VALBERICO FERREIRA DE ARAUJO",
    "GRUPO GERENCIAL": "DESCARTAVEL COLA OURO 2000 ML",
    "META": 385,
    "QTDE": 460,
    "FAT": 11274.86,
    "PM": 24.5106
  },
  {
    "DATA": "2025-10-01T04:00:00.000Z",
    "VENDEDOR": "7880 - VALBERICO FERREIRA DE ARAUJO",
    "GRUPO GERENCIAL": "DESCARTAVEL SABORES 2000 ML",
    "META": 3395,
    "QTDE": 2387,
    "FAT": 55529.38,
    "PM": 23.2633
  },
  {
    "DATA": "2025-10-01T04:00:00.000Z",
    "VENDEDOR": "7881 - VALBERICO FERREIRA DE ARAUJO",
    "GRUPO GERENCIAL": "DESCARTAVEL BC 2000 ML",
    "META": 50,
    "QTDE": 342,
    "FAT": 7343.14,
    "PM": 21.4712
  },
  {
    "DATA": "2025-10-01T04:00:00.000Z",
    "VENDEDOR": "7882 - VALBERICO FERREIRA DE ARAUJO",
    "GRUPO GERENCIAL": "DESCARTAVEL AGUA ",
    "META": 1006.9608,
    "QTDE": 2660,
    "FAT": 32911.88,
    "PM": 12.3729
  },
  {
    "DATA": "2025-10-01T04:00:00.000Z",
    "VENDEDOR": "7883 - VALBERICO FERREIRA DE ARAUJO",
    "GRUPO GERENCIAL": "DESCARTAVEL ENERGETICO",
    "META": 110,
    "QTDE": 45,
    "FAT": 1294.98,
    "PM": 28.7773
  },
  {
    "DATA": "2025-10-01T04:00:00.000Z",
    "VENDEDOR": "7884 - VALBERICO FERREIRA DE ARAUJO",
    "GRUPO GERENCIAL": "SUCO RECONSTITUIDO GAROTO",
    "META": 1048,
    "QTDE": 506.1667,
    "FAT": 43085.3,
    "PM": 85.1208
  },
  {
    "DATA": "2025-10-01T04:00:00.000Z",
    "VENDEDOR": "7885 - VALBERICO FERREIRA DE ARAUJO",
    "GRUPO GERENCIAL": "SUCOS",
    "META": 255,
    "QTDE": 269,
    "FAT": 24826.42,
    "PM": 92.2915
  },
  {
    "DATA": "2025-10-01T04:00:00.000Z",
    "VENDEDOR": "7886 - VALBERICO FERREIRA DE ARAUJO",
    "GRUPO GERENCIAL": "LATA BALY 473 ML",
    "META": 0,
    "QTDE": 1,
    "FAT": 0,
    "PM": 0
  }
]
